dkb_robo/__init__.py
dkb_robo/__main__.py
dkb_robo/authentication.py
dkb_robo/cli.py
dkb_robo/dkb_robo.py
dkb_robo/exemptionorder.py
dkb_robo/legacy.py
dkb_robo/portfolio.py
dkb_robo/postbox.py
dkb_robo/standingorder.py
dkb_robo/transaction.py
dkb_robo/utilities.py
dkb_robo-0.31.2.dist-info/METADATA
dkb_robo-0.31.2.dist-info/WHEEL
dkb_robo-0.31.2.dist-info/entry_points.txt
dkb_robo-0.31.2.dist-info/licenses/LICENSE
dkb_robo-0.31.2.dist-info/RECORD
