Metadata-Version: 2.4
Name: dkb_robo
Version: 0.31.2
Summary: Download transactions from the website of Deutsche Kreditbak AG
Project-URL: Repository, https://github.com/grindsa/dkb-robo
Project-URL: Issues, https://github.com/grindsa/dkb-robo/issues
Author-email: grindsa <grindelsack@gmail.com>
License-File: LICENSE
Keywords: DKB,Deutsche Kreditbank
Classifier: Development Status :: 4 - Beta
Classifier: Intended Audience :: Developers
Classifier: License :: OSI Approved :: GNU General Public License v3 or later (GPLv3+)
Classifier: Natural Language :: German
Classifier: Operating System :: OS Independent
Classifier: Programming Language :: Python :: 3
Classifier: Programming Language :: Python :: 3.8
Classifier: Programming Language :: Python :: 3.9
Classifier: Programming Language :: Python :: 3.10
Classifier: Programming Language :: Python :: 3.11
Classifier: Programming Language :: Python :: 3.12
Classifier: Programming Language :: Python :: 3.13
Classifier: Topic :: Software Development :: Libraries :: Python Modules
Requires-Python: >=3.8
Requires-Dist: bs4
Requires-Dist: click
Requires-Dist: mechanicalsoup
Requires-Dist: pillow
Requires-Dist: requests
Requires-Dist: tabulate
Provides-Extra: dev
Requires-Dist: build; extra == 'dev'
Requires-Dist: html5lib; extra == 'dev'
Requires-Dist: pre-commit; extra == 'dev'
Requires-Dist: pytest; extra == 'dev'
Requires-Dist: pytest-cov; extra == 'dev'
Provides-Extra: test
Requires-Dist: html5lib; extra == 'test'
Requires-Dist: pytest; extra == 'test'
Requires-Dist: pytest-cov; extra == 'test'
